{
  "puzzleId": "daily-2026-01-21-product-management",
  "theme": "Launch Mode",
  "config": {
    "selectionModel": "RAY_4DIR",
    "connectivityModel": "ORTHO_4",
    "allowReverseSelection": false
  },
  "grid": {
    "width": 6,
    "height": 6,
    "cells": [
      {
        "id": "r0c0",
        "x": 0,
        "y": 0,
        "type": "LETTER",
        "value": "M"
      },
      {
        "id": "r0c1",
        "x": 1,
        "y": 0,
        "type": "LETTER",
        "value": "S"
      },
      {
        "id": "r0c2",
        "x": 2,
        "y": 0,
        "type": "LETTER",
        "value": "C"
      },
      {
        "id": "r0c3",
        "x": 3,
        "y": 0,
        "type": "LETTER",
        "value": "O"
      },
      {
        "id": "r0c4",
        "x": 4,
        "y": 0,
        "type": "LETTER",
        "value": "P"
      },
      {
        "id": "r0c5",
        "x": 5,
        "y": 0,
        "type": "LETTER",
        "value": "E"
      },
      {
        "id": "r1c0",
        "x": 0,
        "y": 1,
        "type": "LETTER",
        "value": "V"
      },
      {
        "id": "r1c1",
        "x": 1,
        "y": 1,
        "type": "LETTER",
        "value": "A"
      },
      {
        "id": "r1c2",
        "x": 2,
        "y": 1,
        "type": "LETTER",
        "value": "H"
      },
      {
        "id": "r1c3",
        "x": 3,
        "y": 1,
        "type": "LETTER",
        "value": "K"
      },
      {
        "id": "r1c4",
        "x": 4,
        "y": 1,
        "type": "LETTER",
        "value": "B"
      },
      {
        "id": "r1c5",
        "x": 5,
        "y": 1,
        "type": "LETTER",
        "value": "K"
      },
      {
        "id": "r2c0",
        "x": 0,
        "y": 2,
        "type": "LETTER",
        "value": "M"
      },
      {
        "id": "r2c1",
        "x": 1,
        "y": 2,
        "type": "LETTER",
        "value": "I"
      },
      {
        "id": "r2c2",
        "x": 2,
        "y": 2,
        "type": "LETTER",
        "value": "U"
      },
      {
        "id": "r2c3",
        "x": 3,
        "y": 2,
        "type": "LETTER",
        "value": "B"
      },
      {
        "id": "r2c4",
        "x": 4,
        "y": 2,
        "type": "LETTER",
        "value": "L"
      },
      {
        "id": "r2c5",
        "x": 5,
        "y": 2,
        "type": "LETTER",
        "value": "I"
      },
      {
        "id": "r3c0",
        "x": 0,
        "y": 3,
        "type": "LETTER",
        "value": "W"
      },
      {
        "id": "r3c1",
        "x": 1,
        "y": 3,
        "type": "LETTER",
        "value": "E"
      },
      {
        "id": "r3c2",
        "x": 2,
        "y": 3,
        "type": "LETTER",
        "value": "R"
      },
      {
        "id": "r3c3",
        "x": 3,
        "y": 3,
        "type": "LETTER",
        "value": "V"
      },
      {
        "id": "r3c4",
        "x": 4,
        "y": 3,
        "type": "LETTER",
        "value": "D"
      },
      {
        "id": "r3c5",
        "x": 5,
        "y": 3,
        "type": "LETTER",
        "value": "P"
      },
      {
        "id": "r4c0",
        "x": 0,
        "y": 4,
        "type": "LETTER",
        "value": "W"
      },
      {
        "id": "r4c1",
        "x": 1,
        "y": 4,
        "type": "LETTER",
        "value": "I"
      },
      {
        "id": "r4c2",
        "x": 2,
        "y": 4,
        "type": "LETTER",
        "value": "N"
      },
      {
        "id": "r4c3",
        "x": 3,
        "y": 4,
        "type": "LETTER",
        "value": "E"
      },
      {
        "id": "r4c4",
        "x": 4,
        "y": 4,
        "type": "LETTER",
        "value": "E"
      },
      {
        "id": "r4c5",
        "x": 5,
        "y": 4,
        "type": "LETTER",
        "value": "D"
      },
      {
        "id": "r5c0",
        "x": 0,
        "y": 5,
        "type": "LETTER",
        "value": "J"
      },
      {
        "id": "r5c1",
        "x": 1,
        "y": 5,
        "type": "LETTER",
        "value": "I"
      },
      {
        "id": "r5c2",
        "x": 2,
        "y": 5,
        "type": "LETTER",
        "value": "S"
      },
      {
        "id": "r5c3",
        "x": 3,
        "y": 5,
        "type": "LETTER",
        "value": "P"
      },
      {
        "id": "r5c4",
        "x": 4,
        "y": 5,
        "type": "LETTER",
        "value": "V"
      },
      {
        "id": "r5c5",
        "x": 5,
        "y": 5,
        "type": "LETTER",
        "value": "S"
      }
    ],
    "start": {
      "adjacentCellId": "r0c2"
    },
    "end": {
      "adjacentCellId": "r5c4"
    }
  },
  "words": {
    "path": [
      {
        "wordId": "CHURN",
        "tokens": [
          {
            "t": "L",
            "v": "C"
          },
          {
            "t": "L",
            "v": "H"
          },
          {
            "t": "L",
            "v": "U"
          },
          {
            "t": "L",
            "v": "R"
          },
          {
            "t": "L",
            "v": "N"
          }
        ],
        "size": 5,
        "placements": [
          [
            "r0c2",
            "r1c2",
            "r2c2",
            "r3c2",
            "r4c2"
          ]
        ]
      },
      {
        "wordId": "SCOPE",
        "tokens": [
          {
            "t": "L",
            "v": "S"
          },
          {
            "t": "L",
            "v": "C"
          },
          {
            "t": "L",
            "v": "O"
          },
          {
            "t": "L",
            "v": "P"
          },
          {
            "t": "L",
            "v": "E"
          }
        ],
        "size": 5,
        "placements": [
          [
            "r0c1",
            "r0c2",
            "r0c3",
            "r0c4",
            "r0c5"
          ]
        ]
      },
      {
        "wordId": "NEED",
        "tokens": [
          {
            "t": "L",
            "v": "N"
          },
          {
            "t": "L",
            "v": "E"
          },
          {
            "t": "L",
            "v": "E"
          },
          {
            "t": "L",
            "v": "D"
          }
        ],
        "size": 4,
        "placements": [
          [
            "r4c2",
            "r4c3",
            "r4c4",
            "r4c5"
          ]
        ]
      },
      {
        "wordId": "DEV",
        "tokens": [
          {
            "t": "L",
            "v": "D"
          },
          {
            "t": "L",
            "v": "E"
          },
          {
            "t": "L",
            "v": "V"
          }
        ],
        "size": 3,
        "placements": [
          [
            "r3c4",
            "r4c4",
            "r5c4"
          ]
        ]
      }
    ],
    "additional": [
      {
        "wordId": "WIN",
        "tokens": [
          {
            "t": "L",
            "v": "W"
          },
          {
            "t": "L",
            "v": "I"
          },
          {
            "t": "L",
            "v": "N"
          }
        ],
        "size": 3,
        "placements": [
          [
            "r4c0",
            "r4c1",
            "r4c2"
          ]
        ],
        "hintCellId": "r4c2"
      }
    ]
  }
}