{
  "version": 1,
  "contentVersion": "2026.01.17-v2",
  "topicId": "cybersecurity",
  "title": "Cybersecurity",
  "description": "Threat modeling, encryption, authentication, attacks.",
  "icon": "🔒",
  "puzzles": [
    {
      "id": "daily-2026-01-17-cybersecurity",
      "revision": 1,
      "title": "Breach Alert",
      "difficulty": "easy",
      "grid": {
        "width": 6,
        "height": 6
      },
      "estimatedMinutes": 3,
      "tags": [],
      "puzzlePath": "/daily/2026-01-17-cybersecurity.json",
      "createdAt": "2026-01-17"
    },
    {
      "id": "daily-2026-01-18-cybersecurity",
      "revision": 1,
      "title": "Secure Mode",
      "difficulty": "easy",
      "grid": {
        "width": 6,
        "height": 6
      },
      "estimatedMinutes": 3,
      "tags": [],
      "puzzlePath": "/daily/2026-01-18-cybersecurity.json",
      "createdAt": "2026-01-18"
    },
    {
      "id": "daily-2026-01-19-cybersecurity",
      "revision": 1,
      "title": "Firewall Up",
      "difficulty": "easy",
      "grid": {
        "width": 6,
        "height": 6
      },
      "estimatedMinutes": 3,
      "tags": [],
      "puzzlePath": "/daily/2026-01-19-cybersecurity.json",
      "createdAt": "2026-01-19"
    },
    {
      "id": "daily-2026-01-20-cybersecurity",
      "revision": 1,
      "title": "Threat Hunt",
      "difficulty": "easy",
      "grid": {
        "width": 6,
        "height": 6
      },
      "estimatedMinutes": 3,
      "tags": [],
      "puzzlePath": "/daily/2026-01-20-cybersecurity.json",
      "createdAt": "2026-01-20"
    },
    {
      "id": "daily-2026-01-21-cybersecurity",
      "revision": 1,
      "title": "Crypto Quest",
      "difficulty": "easy",
      "grid": {
        "width": 6,
        "height": 6
      },
      "estimatedMinutes": 3,
      "tags": [],
      "puzzlePath": "/daily/2026-01-21-cybersecurity.json",
      "createdAt": "2026-01-21"
    },
    {
      "id": "daily-2026-01-22-cybersecurity",
      "revision": 1,
      "title": "Breach Alert",
      "difficulty": "easy",
      "grid": {
        "width": 6,
        "height": 6
      },
      "estimatedMinutes": 3,
      "tags": [],
      "puzzlePath": "/daily/2026-01-22-cybersecurity.json",
      "createdAt": "2026-01-22"
    },
    {
      "id": "daily-2026-01-23-cybersecurity",
      "revision": 1,
      "title": "Secure Mode",
      "difficulty": "easy",
      "grid": {
        "width": 6,
        "height": 6
      },
      "estimatedMinutes": 3,
      "tags": [],
      "puzzlePath": "/daily/2026-01-23-cybersecurity.json",
      "createdAt": "2026-01-23"
    }
  ]
}